{
  "products": [
    {
      "id": "1",
      "name": "Wireless Headphones",
      "slug": "wireless-headphones",
      "description": "Premium noise-cancelling wireless headphones with 30-hour battery life",
      "price": 299.99,
      "compareAtPrice": 399.99,
      "images": [
        "/images/headphones.jpg"
      ],
      "category": "Electronics",
      "inventory": 50,
      "isActive": true
    },
    {
      "id": "2",
      "name": "Smart Watch",
      "slug": "smart-watch",
      "description": "Fitness tracking smartwatch with heart rate monitor and GPS",
      "price": 249.99,
      "compareAtPrice": null,
      "images": [
        "/images/watch.jpg"
      ],
      "category": "Electronics",
      "inventory": 30,
      "isActive": true
    },
    {
      "id": "3",
      "name": "Running Shoes",
      "slug": "running-shoes",
      "description": "Lightweight running shoes with advanced cushioning technology",
      "price": 129.99,
      "compareAtPrice": 159.99,
      "images": [
        "/images/shoes.jpg"
      ],
      "category": "Fashion",
      "inventory": 100,
      "isActive": true
    },
    {
      "id": "4",
      "name": "Coffee Maker",
      "slug": "coffee-maker",
      "description": "Programmable coffee maker with thermal carafe",
      "price": 89.99,
      "compareAtPrice": null,
      "images": [
        "/images/coffee.jpg"
      ],
      "category": "Home",
      "inventory": 25,
      "isActive": true
    },
    {
      "id": "5",
      "name": "Yoga Mat",
      "slug": "yoga-mat",
      "description": "Non-slip eco-friendly yoga mat with carrying strap",
      "price": 39.99,
      "compareAtPrice": 49.99,
      "images": [
        "/images/yoga.jpg"
      ],
      "category": "Sports",
      "inventory": 75,
      "isActive": true
    }
  ],
  "cart": [
    {
      "id": "173e",
      "productId": "3",
      "quantity": 1,
      "product": {
        "id": "3",
        "name": "Running Shoes",
        "slug": "running-shoes",
        "description": "Lightweight running shoes with advanced cushioning technology",
        "price": 129.99,
        "compareAtPrice": 159.99,
        "images": [
          "/images/shoes.jpg"
        ],
        "category": "Fashion",
        "inventory": 100,
        "isActive": true
      }
    }
  ],
  "orders": []
}